dolpa/__init__.py
dolpa/comparator.py
dolpa/dolpa.py
dolpa/dolpa_logger.py
dolpa/dolpa_utils.py
dolpa/exceptions.py
dolpa-0.1.41.dist-info/LICENSE
dolpa-0.1.41.dist-info/METADATA
dolpa-0.1.41.dist-info/WHEEL
dolpa-0.1.41.dist-info/RECORD
