Metadata-Version: 2.1
Name: dolpa
Version: 0.1.41
Summary: Simple and elegant framework for automating your API tests
Home-page: https://github.com/ggautams/dolpa
Author: ggautam
Author-email: gpal.gtm@gmail.com
Requires-Python: >=3.7,<4.0
Classifier: Programming Language :: Python :: 3
Classifier: Programming Language :: Python :: 3.7
Classifier: Programming Language :: Python :: 3.8
Classifier: Programming Language :: Python :: 3.9
Classifier: Programming Language :: Python :: 3.10
Classifier: Programming Language :: Python :: 3.11
Requires-Dist: requests (>=2.31.0,<3.0.0)
Project-URL: Documentation, https://github.com/ggautams/dolpa/blob/main/README.md
Project-URL: Repository, https://github.com/ggautams/dolpa
